zdrive/__init__.py
zdrive/version.py
zdrive/base/__init__.py
zdrive/base/base.py
zdrive/download/__init__.py
zdrive/download/downloader.py
zdrive/upload/__init__.py
zdrive/upload/uploader.py
ZDrive-2.1.5.dist-info/LICENSE
ZDrive-2.1.5.dist-info/METADATA
ZDrive-2.1.5.dist-info/WHEEL
ZDrive-2.1.5.dist-info/top_level.txt
ZDrive-2.1.5.dist-info/RECORD
