Metadata-Version: 2.1
Name: ZDrive
Version: 2.1.5
Summary: A lightweight module to download and upload data to Google Drive contents
Home-page: https://github.com/ab-anand/Zdrive
Download-URL: https://github.com/ab-anand/zdrive/tarball/2.1.5
Author: Abhinav Anand
Author-email: abhinavanand1905@gmail.com
License: MIT
Keywords: Google Drive,Utility,Automation,File management,File Organizer
Classifier: Intended Audience :: Developers
Classifier: License :: OSI Approved :: MIT License
Classifier: Natural Language :: English
Classifier: Programming Language :: Python
Classifier: Programming Language :: Python :: 2.7
Classifier: Programming Language :: Python :: 3.4
Classifier: Programming Language :: Python :: 3.6
Classifier: Programming Language :: Python :: 3.8
Classifier: Topic :: System
Classifier: Topic :: System :: Operating System
Classifier: Topic :: Utilities
Classifier: Topic :: Software Development
Classifier: Topic :: Software Development :: Libraries
License-File: LICENSE
Requires-Dist: pathlib (>=1.0.1)
Requires-Dist: setuptools (>=44.1.1)
Requires-Dist: google-auth-oauthlib (>=0.4.4)
